akida/__init__.py
akida/__main__.py
akida/akida.dll
akida/akida.lib
akida/cli.py
akida/core.pyd
akida/layer.py
akida/libomp.dll
akida/mapping.py
akida/model.py
akida/np.py
akida/sequence.py
akida/statistics.py
akida/virtual_devices.py
akida/api/akida/backend_type.h
akida/api/akida/backends.h
akida/api/akida/device.h
akida/api/akida/hardware_component.h
akida/api/akida/layer.h
akida/api/akida/layer_params.h
akida/api/akida/learning_params.h
akida/api/akida/map_constraints.h
akida/api/akida/mesh.h
akida/api/akida/model.h
akida/api/akida/sequence.h
akida/api/akida/sram_size.h
akida/api/akida/variable_helpers.h
akida/api/akida/variables.h
akida/api/host/akd1500_spiflash_controller.h
akida/api/host/circular_queue.h
akida/api/host/environment.h
akida/api/host/flash_access_driver.h
akida/api/host/hardware_devices.h
akida/api/host/hardware_drivers.h
akida/api/host/host_device.h
akida/api/host/power_meter.h
akida/api/host/soc_clock_mode.h
akida/api/host/soc_driver.h
akida/api/infra/exports.h
akida/api/infra/hardware_driver.h
akida/api/infra/int_ops.h
akida/api/infra/registers_common.h
akida/api/infra/system.h
akida/boards/__init__.py
akida/boards/akd1500/__init__.py
akida/boards/akd1500/spi_flash.py
akida/deploy/__init__.py
akida/deploy/engine.py
akida/engine/CMakeLists.txt
akida/engine/README.md
akida/engine/api/akd1000/bare_metal_driver.h
akida/engine/api/akd1000/memory_mapping.h
akida/engine/api/akd1000/registers_soc.h
akida/engine/api/akd1500/abstract_spi_driver.h
akida/engine/api/akd1500/akd1500_spi_driver.h
akida/engine/api/akd1500/memory_mapping.h
akida/engine/api/akd1500/spi_flash.h
akida/engine/api/akida/dense.h
akida/engine/api/akida/hardware_device.h
akida/engine/api/akida/hardware_ident.h
akida/engine/api/akida/hardware_type.h
akida/engine/api/akida/hw_version.h
akida/engine/api/akida/input_conversion.h
akida/engine/api/akida/ip_version.h
akida/engine/api/akida/np.h
akida/engine/api/akida/program_info.h
akida/engine/api/akida/program_memory_info.h
akida-2.18.2.dist-info/licenses/LICENSE
akida-2.18.2.dist-info/licenses/LICENSE.3rdparty
akida-2.18.2.dist-info/METADATA
akida-2.18.2.dist-info/WHEEL
akida-2.18.2.dist-info/entry_points.txt
akida-2.18.2.dist-info/top_level.txt
akida-2.18.2.dist-info/RECORD
