Metadata-Version: 2.4
Name: akida
Version: 2.18.2
Summary: Akida Execution Engine
Home-page: https://doc.brainchipinc.com
Author: Matthieu Hernandez
Author-email: hmatthieu@brainchip.com
License: Proprietary
Requires-Python: >=3.10
License-File: LICENSE
License-File: LICENSE.3rdparty
Requires-Dist: numpy
Dynamic: author
Dynamic: author-email
Dynamic: description
Dynamic: description-content-type
Dynamic: home-page
Dynamic: license
Dynamic: license-file
Dynamic: requires-dist
Dynamic: requires-python
Dynamic: summary
